dimsum/__init__.py
dimsum/core/__init__.py
dimsum/core/feature_metadata.py
dimsum/core/feature_set.py
dimsum/core/metadata_builder.py
dimsum/core/store.py
dimsum/decorators/__init__.py
dimsum/decorators/datasource.py
dimsum/decorators/metadata.py
dimsum/providers/__init__.py
dimsum/providers/cache/__init__.py
dimsum/providers/cache/cache.py
dimsum/providers/cache/cache_factory.py
dimsum/providers/cache/cache_registry_base.py
dimsum/providers/cache/cache_registry_factory.py
dimsum/providers/cache/flatfile_cache_registry.py
dimsum/providers/cache/ibm_object_storage_cache_registry.py
dimsum/providers/cache/null_cache.py
dimsum/providers/cache/redis_cache_registry.py
dimsum/providers/dataframe/__init__.py
dimsum/providers/dataframe/processor_factory.py
dimsum/providers/dataframe/column/__init__.py
dimsum/providers/dataframe/column/normalizer/__init__.py
dimsum/providers/dataframe/column/normalizer/normalizer_base.py
dimsum/providers/dataframe/column/normalizer/pandas_normalizer.py
dimsum/providers/dataframe/column/normalizer/pyspark_normalizer.py
dimsum/providers/dataframe/converter/__init__.py
dimsum/providers/dataframe/converter/converter_base.py
dimsum/providers/dataframe/converter/pandas_converter.py
dimsum/providers/dataframe/converter/pyspark_converter.py
dimsum/providers/dataframe/jointer/__init__.py
dimsum/providers/dataframe/jointer/jointer_base.py
dimsum/providers/dataframe/jointer/pandas_jointer.py
dimsum/providers/dataframe/jointer/pyspark_jointer.py
dimsum/providers/meta_manager/__init__.py
dimsum/providers/meta_manager/flatfile_meta_manager.py
dimsum/providers/meta_manager/ibm_object_storage_meta_manager.py
dimsum/providers/meta_manager/ibm_wkc_meta_manager.py
dimsum/providers/meta_manager/meta_manager_base.py
dimsum/providers/meta_manager/meta_manager_factory.py
dimsum/providers/output_render/__init__.py
dimsum/providers/output_render/html_render.py
dimsum/providers/output_render/output_render_base.py
DimStore-0.1.1.dist-info/LICENSE
DimStore-0.1.1.dist-info/METADATA
DimStore-0.1.1.dist-info/WHEEL
DimStore-0.1.1.dist-info/top_level.txt
DimStore-0.1.1.dist-info/zip-safe
DimStore-0.1.1.dist-info/RECORD
