Metadata-Version: 2.1
Name: DimStore
Version: 0.1.1
Summary: DimStore is a project that aims to enable the collaboration of Data Science at the lowest and richest level.
Home-page: 
Author: Kai Niu
Author-email: kai.niu@ibm.com
License: BSD 2-Clause License
Keywords: feature store,data science,pipeline
Platform: UNKNOWN
Classifier: Programming Language :: Python :: 3
Classifier: License :: OSI Approved :: MIT License
Classifier: Operating System :: OS Independent
Classifier: Programming Language :: Python
Classifier: Programming Language :: Python :: 3
Classifier: Programming Language :: Python :: 3.4
Classifier: Programming Language :: Python :: 3.5
Classifier: Programming Language :: Python :: 3.6
Classifier: Programming Language :: Python :: 3.7
Classifier: Programming Language :: Python :: Implementation :: CPython
Classifier: Programming Language :: Python :: Implementation :: PyPy
Classifier: Topic :: Utilities
Requires-Python: >=3.6
Requires-Dist: dill (~=0.2.9)
Requires-Dist: pickleshare (~=0.7.5)
Requires-Dist: botocore (~=1.12.201)
Requires-Dist: ibm-cos-sdk (~=2.5.2)
Requires-Dist: ibm-cos-sdk-core (~=2.5.2)
Requires-Dist: ibm-cos-sdk-s3transfer (~=2.5.2)
Requires-Dist: pyspark (~=2.4.0)
Requires-Dist: pygithub (~=1.55)
Requires-Dist: redis (~=3.5.3)
Requires-Dist: pyyaml (>=5.4.0)
Provides-Extra: dev
Provides-Extra: test
Requires-Dist: pytest ; extra == 'test'
Requires-Dist: pytest-cov ; extra == 'test'
Requires-Dist: mock ; extra == 'test'
